{
  "students": [
    {
      "name": "Hoàng Văn Học",
      "age": 22,
      "classes": [
        "REACTJS_7103SE",
        "NODEJS_2107",
        "SQL-XAMPP",
        "CD19CNTT2"
      ],
      "addr": "BG",
      "course": "2019",
      "specialized": "CNTT",
      "imgUrl": "https://firebasestorage.googleapis.com/v0/b/fir-upload-db77d.appspot.com/o/image%2Ftuanphuc.JPG?alt=media&token=d2f39a2a-5a72-4620-8e4a-e7e520291b08",
      "info": {
        "accommodations": "BR-VT",
        "birth": "1999-11-17",
        "nation": "Kinh",
        "religion": "Không",
        "mssv": "123456789",
        "union": "2001-11-17",
        "cmnd": "122340733",
        "bhyt": "1214123543535",
        "phone": "0695521332",
        "email": "hoc17112001@gmail.com"
      },
      "id": 1,
      "gender": "Nam",
      "roles": "Không",
      "levelEducate": "Cao đẳng",
      "typeEducate": "Chính quy"
    },
    {
      "name": "Ngọ Văn Tuấn",
      "age": 20,
      "classes": [],
      "addr": "HN",
      "course": "2019",
      "specialized": "CNTT",
      "imgUrl": "https://firebasestorage.googleapis.com/v0/b/fir-upload-db77d.appspot.com/o/image%2Ftuanphuc.JPG?alt=media&token=f1164e8c-9138-4470-a3b8-9e9e19f88ba9",
      "info": {
        "accommodations": "",
        "birth": "",
        "nation": "",
        "religion": "",
        "mssv": "123153123",
        "union": "",
        "cmnd": "",
        "bhyt": "",
        "phone": "",
        "email": ""
      },
      "id": 3,
      "gender": "Nữ",
      "roles": "Hót cức",
      "levelEducate": "Đại học",
      "typeEducate": "Chính quy"
    },
    {
      "name": "Hoàng Thế Anh",
      "age": "20",
      "classes": [
        "SQL-XAMPP"
      ],
      "addr": "BG",
      "course": "2019",
      "specialized": "CNTT",
      "imgUrl": "https://firebasestorage.googleapis.com/v0/b/fir-upload-db77d.appspot.com/o/image%2Ftheanh2.jpg?alt=media&token=29ee6159-fbe2-41ea-8685-06dea137884c",
      "info": {
        "accommodations": "",
        "birth": "",
        "nation": "",
        "religion": "",
        "mssv": "1234566",
        "union": "",
        "cmnd": "",
        "bhyt": "",
        "phone": "",
        "email": ""
      },
      "id": 7,
      "gender": "Nam",
      "roles": "Không",
      "levelEducate": "Đại học",
      "typeEducate": "Chính quy",
      "union": "",
      "cmnd": "",
      "bhyt": "",
      "phone": "",
      "email": ""
    },
    {
      "name": "Ngọ Xuân Hiếu",
      "age": "21",
      "classes": [
        "REACTJS_7103SE"
      ],
      "addr": "Bắc Giang",
      "course": "2019",
      "specialized": "Blowjob",
      "imgUrl": "https://firebasestorage.googleapis.com/v0/b/fir-upload-db77d.appspot.com/o/image%2Fhieutri.jpg?alt=media&token=c7f62851-f376-4f6c-b8f0-50f05b5d499d",
      "info": {
        "accommodations": "",
        "birth": "",
        "nation": "",
        "religion": "",
        "mssv": "66771508",
        "union": "",
        "cmnd": "",
        "bhyt": "",
        "phone": "",
        "email": ""
      },
      "id": 8,
      "gender": "Nữ",
      "roles": "Buscu",
      "levelEducate": "Đại học",
      "typeEducate": "Chính quy"
    },
    {
      "name": "Nguyễn Văn Thuần",
      "age": 20,
      "classes": [
        "REACTJS-7103",
        "SQL-XAMPP",
        "NODEJS_2107"
      ],
      "addr": "HH-BG",
      "course": "2019",
      "specialized": "CNTT",
      "imgUrl": "https://firebasestorage.googleapis.com/v0/b/fir-upload-db77d.appspot.com/o/image%2Fthuanngu.jpg?alt=media&token=fccfbb3b-a55a-444d-9a63-95f187bf9709",
      "info": {
        "accommodations": "HN",
        "birth": "2001-01-01",
        "nation": "Kinh",
        "religion": "Không",
        "mssv": "123445567",
        "union": "2019-09-29",
        "cmnd": "122340742",
        "bhyt": "1241512353243",
        "phone": "0987213456",
        "email": "thuanmeo1342@gmail.com"
      },
      "id": 13,
      "gender": "Nam",
      "roles": "Thực tập sinh",
      "levelEducate": "Cao đẳng",
      "typeEducate": "Chính quy"
    },
    {
      "name": "Lê Văn Hậu",
      "age": 20,
      "classes": [
        "CD19CNTT2",
        "SQL-XAMPP"
      ],
      "addr": "BR-VT",
      "course": "2019",
      "specialized": "CNTT",
      "imgUrl": "https://firebasestorage.googleapis.com/v0/b/fir-upload-db77d.appspot.com/o/image%2Fkonan.jpg?alt=media&token=d30638e6-e597-40e3-abff-b373655b2797",
      "info": {
        "accommodations": "BR-VT",
        "birth": "2001-09-15",
        "nation": "Kinh",
        "religion": "Không",
        "mssv": "153246433",
        "union": "2018-05-17",
        "cmnd": "213144352332",
        "bhyt": "215123545432432",
        "phone": "0967566534",
        "email": "levanhau@gmail.com"
      },
      "gender": "Nam",
      "roles": "Không",
      "levelEducate": "Cao đẳng",
      "typeEducate": "Chính quy",
      "id": 14
    },
    {
      "name": "test",
      "age": "23",
      "classes": [
        "REACTJS_7103SE"
      ],
      "addr": "BR-VT",
      "course": "",
      "specialized": "CNTT",
      "imgUrl": "https://firebasestorage.googleapis.com/v0/b/fir-upload-db77d.appspot.com/o/image%2Fkonan.jpg?alt=media&token=d30638e6-e597-40e3-abff-b373655b2797",
      "info": {
        "accommodations": "",
        "birth": "",
        "nation": "",
        "religion": "",
        "mssv": "",
        "union": "",
        "cmnd": "",
        "bhyt": "",
        "phone": "",
        "email": ""
      },
      "gender": "",
      "roles": "",
      "levelEducate": "",
      "typeEducate": "",
      "id": 15
    },
    {
      "name": "test",
      "age": "23",
      "classes": [
        "REACTJS_7103SE"
      ],
      "addr": "BR-VT",
      "course": "",
      "specialized": "CNTT",
      "imgUrl": "https://firebasestorage.googleapis.com/v0/b/fir-upload-db77d.appspot.com/o/image%2Fkonan.jpg?alt=media&token=d30638e6-e597-40e3-abff-b373655b2797",
      "info": {
        "accommodations": "",
        "birth": "",
        "nation": "",
        "religion": "",
        "mssv": "",
        "union": "",
        "cmnd": "",
        "bhyt": "",
        "phone": "",
        "email": ""
      },
      "gender": "",
      "roles": "",
      "levelEducate": "",
      "typeEducate": "",
      "id": 16
    },
    {
      "name": "test",
      "age": "23",
      "classes": [
        "REACTJS_7103SE"
      ],
      "addr": "BR-VT",
      "course": "",
      "specialized": "CNTT",
      "imgUrl": "https://firebasestorage.googleapis.com/v0/b/fir-upload-db77d.appspot.com/o/image%2Fkonan.jpg?alt=media&token=d30638e6-e597-40e3-abff-b373655b2797",
      "info": {
        "accommodations": "",
        "birth": "",
        "nation": "",
        "religion": "",
        "mssv": "",
        "union": "",
        "cmnd": "",
        "bhyt": "",
        "phone": "",
        "email": ""
      },
      "gender": "",
      "roles": "",
      "levelEducate": "",
      "typeEducate": "",
      "id": 17
    },
    {
      "name": "test",
      "age": "23",
      "classes": [
        "REACTJS_7103SE"
      ],
      "addr": "BR-VT",
      "course": "",
      "specialized": "CNTT",
      "imgUrl": "https://firebasestorage.googleapis.com/v0/b/fir-upload-db77d.appspot.com/o/image%2Fkonan.jpg?alt=media&token=d30638e6-e597-40e3-abff-b373655b2797",
      "info": {
        "accommodations": "",
        "birth": "",
        "nation": "",
        "religion": "",
        "mssv": "",
        "union": "",
        "cmnd": "",
        "bhyt": "",
        "phone": "",
        "email": ""
      },
      "gender": "",
      "roles": "",
      "levelEducate": "",
      "typeEducate": "",
      "id": 18
    },
    {
      "name": "test",
      "age": "23",
      "classes": [
        "REACTJS_7103SE"
      ],
      "addr": "BR-VT",
      "course": "",
      "specialized": "CNTT",
      "imgUrl": "https://firebasestorage.googleapis.com/v0/b/fir-upload-db77d.appspot.com/o/image%2Fkonan.jpg?alt=media&token=d30638e6-e597-40e3-abff-b373655b2797",
      "info": {
        "accommodations": "",
        "birth": "",
        "nation": "",
        "religion": "",
        "mssv": "",
        "union": "",
        "cmnd": "",
        "bhyt": "",
        "phone": "",
        "email": ""
      },
      "gender": "",
      "roles": "",
      "levelEducate": "",
      "typeEducate": "",
      "id": 19
    },
    {
      "name": "test",
      "age": "23",
      "classes": [
        "REACTJS_7103SE"
      ],
      "addr": "BR-VT",
      "course": "",
      "specialized": "CNTT",
      "imgUrl": "https://firebasestorage.googleapis.com/v0/b/fir-upload-db77d.appspot.com/o/image%2Fkonan.jpg?alt=media&token=d30638e6-e597-40e3-abff-b373655b2797",
      "info": {
        "accommodations": "",
        "birth": "",
        "nation": "",
        "religion": "",
        "mssv": "",
        "union": "",
        "cmnd": "",
        "bhyt": "",
        "phone": "",
        "email": ""
      },
      "gender": "",
      "roles": "",
      "levelEducate": "",
      "typeEducate": "",
      "id": 20
    },
    {
      "name": "test",
      "age": "23",
      "classes": [
        "REACTJS_7103SE"
      ],
      "addr": "BR-VT",
      "course": "",
      "specialized": "CNTT",
      "imgUrl": "https://firebasestorage.googleapis.com/v0/b/fir-upload-db77d.appspot.com/o/image%2Fkonan.jpg?alt=media&token=d30638e6-e597-40e3-abff-b373655b2797",
      "info": {
        "accommodations": "",
        "birth": "",
        "nation": "",
        "religion": "",
        "mssv": "",
        "union": "",
        "cmnd": "",
        "bhyt": "",
        "phone": "",
        "email": ""
      },
      "gender": "",
      "roles": "",
      "levelEducate": "",
      "typeEducate": "",
      "id": 21
    }
  ],
  "classes": [
    {
      "id": 1,
      "classname": "REACTJS_7103SE"
    },
    {
      "id": 2,
      "classname": "NODEJS_2107"
    },
    {
      "id": 3,
      "classname": "SQL-XAMPP"
    },
    {
      "id": 4,
      "classname": "CD19CNTT2"
    },
    {
      "id": 5,
      "classname": "CNTT-BK HN"
    }
  ],
  "teacherInfo": [
    {
      "name": "Hoàng Văn Học",
      "birth": "1997-11-17",
      "gender": "Nam",
      "teacherExp": "Junior",
      "classes": [
        "NODEJS_2107",
        "CD19CNTT2"
      ],
      "info": {
        "address": "HH-BG",
        "age": 24,
        "email": "",
        "phone": "",
        "bhyt": "",
        "birth": "",
        "location": "",
        "nation": "",
        "religion": "",
        "cmnd": "",
        "union": ""
      },
      "mssgv": "",
      "img": "",
      "workDate": "",
      "id": 5
    },
    {
      "name": "test",
      "birth": "1994-11-17",
      "gender": "Nam",
      "teacherExp": "Trợ giảng",
      "classes": [
        "REACTJS_7103SE"
      ],
      "info": {
        "address": "BG",
        "age": 27,
        "email": "",
        "phone": "",
        "bhyt": "",
        "birth": "",
        "location": "",
        "nation": "",
        "religion": "",
        "cmnd": "",
        "union": ""
      },
      "mssgv": "",
      "img": "",
      "workDate": "",
      "id": 6
    },
    {
      "name": "test",
      "birth": "1994-11-17",
      "gender": "Nam",
      "teacherExp": "Trợ giảng",
      "classes": [
        "REACTJS_7103SE"
      ],
      "info": {
        "address": "BG",
        "age": 27,
        "email": "",
        "phone": "",
        "bhyt": "",
        "birth": "",
        "location": "",
        "nation": "",
        "religion": "",
        "cmnd": "",
        "union": ""
      },
      "mssgv": "",
      "img": "",
      "workDate": "",
      "id": 7
    },
    {
      "name": "test",
      "birth": "1994-11-17",
      "gender": "Nam",
      "teacherExp": "Trợ giảng",
      "classes": [
        "REACTJS_7103SE"
      ],
      "info": {
        "address": "BG",
        "age": 27,
        "email": "",
        "phone": "",
        "bhyt": "",
        "birth": "",
        "location": "",
        "nation": "",
        "religion": "",
        "cmnd": "",
        "union": ""
      },
      "mssgv": "",
      "img": "",
      "workDate": "",
      "id": 8
    },
    {
      "name": "Hoàng Văn Học 3",
      "birth": "2000-11-17",
      "gender": "Nam",
      "teacherExp": "Trợ giảng",
      "classes": [
        "REACTJS_7103SE"
      ],
      "info": {
        "address": "BG",
        "age": 21,
        "email": "",
        "phone": "",
        "bhyt": "",
        "birth": "",
        "location": "",
        "nation": "",
        "religion": "",
        "cmnd": "",
        "union": ""
      },
      "mssgv": "",
      "img": "",
      "workDate": "",
      "id": 20
    },
    {
      "name": "Hoàng Văn Học 4",
      "birth": "2003-11-11",
      "gender": "Nam",
      "teacherExp": "Senior",
      "classes": [
        "NODEJS_2107"
      ],
      "info": {
        "address": "BR-VT",
        "age": 18,
        "email": "",
        "phone": "",
        "bhyt": "",
        "birth": "",
        "location": "",
        "nation": "",
        "religion": "",
        "cmnd": "",
        "union": ""
      },
      "mssgv": "",
      "img": "",
      "workDate": "",
      "id": 21
    },
    {
      "name": "Nguyễn Văn Thuần",
      "birth": "2001-01-01",
      "gender": "Nam",
      "teacherExp": "Fresher",
      "classes": [
        "REACTJS_7103SE"
      ],
      "info": {
        "address": "HH-BG",
        "age": 20,
        "email": "",
        "phone": "",
        "bhyt": "",
        "birth": "",
        "location": "",
        "nation": "",
        "religion": "",
        "cmnd": "",
        "union": ""
      },
      "mssgv": "",
      "img": "",
      "workDate": "",
      "id": 22
    },
    {
      "name": "Hoàng Thế Anh 3",
      "birth": "2001-03-19",
      "gender": "Nam",
      "teacherExp": "Trợ giảng",
      "classes": [
        "CNTT-BK HN"
      ],
      "info": {
        "address": "BG",
        "age": 20,
        "email": "",
        "phone": "",
        "bhyt": "",
        "birth": "",
        "location": "",
        "nation": "",
        "religion": "",
        "cmnd": "",
        "union": ""
      },
      "mssgv": "",
      "img": "",
      "workDate": "",
      "id": 23
    },
    {
      "name": "test",
      "birth": "2000-11-11",
      "gender": "Nữ",
      "teacherExp": "Trợ giảng",
      "classes": [
        "REACTJS_7103SE"
      ],
      "info": {
        "address": "BG",
        "age": 21,
        "email": "",
        "phone": "",
        "bhyt": "",
        "birth": "",
        "location": "",
        "nation": "",
        "religion": "",
        "cmnd": "",
        "union": ""
      },
      "mssgv": "",
      "img": "",
      "workDate": "",
      "id": 24
    }
  ]
}